abraham3k/__init__.py
abraham3k/prophets.py
abraham3k/salt.py
abraham3k/test_prophets.py
abraham3k-1.5.3.dist-info/LICENSE
abraham3k-1.5.3.dist-info/METADATA
abraham3k-1.5.3.dist-info/WHEEL
abraham3k-1.5.3.dist-info/top_level.txt
abraham3k-1.5.3.dist-info/RECORD
