Metadata-Version: 2.1
Name: abraham3k
Version: 1.5.3
Summary: Algorithmically predict public sentiment on a topic using VADER sentiment analysis
Home-page: https://github.com/ckinateder/abraham
Author: Calvin Kinateder
Author-email: calvinkinateder@gmail.com
License: UNKNOWN
Project-URL: Bug Tracker, https://github.com/ckinateder/abraham/issues
Platform: UNKNOWN
Classifier: Programming Language :: Python :: 3
Classifier: License :: OSI Approved :: MIT License
Classifier: Operating System :: OS Independent
Requires-Python: >=3.6
Requires-Dist: nltk (>=3.6.1)
Requires-Dist: newspaper3k (>=0.2.8)
Requires-Dist: GoogleNews (>=1.5.7)
Requires-Dist: pandas (>=1.2.3)
Requires-Dist: tqdm (>=4.58.0)
Requires-Dist: flair (>=0.8.0.post1)
Requires-Dist: twint (>=2.1.20)
